{
    "label": 1,
    "score": 0.0587844448212439,
    "predict_proba": [
        0.4,
        0.03428571428571417
    ],
    "result": [
        {
            "fid": 3,
            "cof": -0.21087130308737592,
            "conflict": -0.14719618753491773
        },
        {
            "fid": 23,
            "cof": -0.07929055986098639,
            "conflict": -0.07723417397991614
        },
        {
            "fid": 2,
            "cof": 0.023963107179995898,
            "conflict": 0.01634806604555397
        },
        {
            "fid": 4,
            "cof": 0.02350496404569778,
            "conflict": 0.016652105899920826
        },
        {
            "fid": 29,
            "cof": -0.018396427722619794,
            "conflict": -0.014475741221780847
        },
        {
            "fid": 6,
            "cof": 0.0171565965976183,
            "conflict": 0.011659098403080211
        },
        {
            "fid": 16,
            "cof": 0.015513441194009103,
            "conflict": 0.011345124616359961
        },
        {
            "fid": 20,
            "cof": -0.013762955968657054,
            "conflict": -0.01045160792576502
        },
        {
            "fid": 5,
            "cof": -0.013143699383608265,
            "conflict": -0.011308812287193323
        },
        {
            "fid": 12,
            "cof": -0.010509484974774042,
            "conflict": -0.008847345917747454
        }
    ]
}