{
    "label": 1,
    "score": 0.25641023810690844,
    "predict_proba": [
        0.22,
        0.08160884317337543,
        0.0,
        0.0,
        0.0,
        0.0,
        0.0
    ],
    "result": [
        {
            "fid": 0,
            "cof": 0.09992495726474894,
            "conflict": -0.021679884216454212
        },
        {
            "fid": 49,
            "cof": -0.08158960156653945,
            "conflict": -0.04601922891046668
        },
        {
            "fid": 13,
            "cof": 0.07810563038070102,
            "conflict": -0.10101840338883791
        },
        {
            "fid": 27,
            "cof": 0.07475288885840432,
            "conflict": -0.014478873051647814
        },
        {
            "fid": 25,
            "cof": -0.07079981045817874,
            "conflict": 0.02023727827933201
        },
        {
            "fid": 51,
            "cof": 0.06476250305472127,
            "conflict": -0.03013279105523216
        },
        {
            "fid": 35,
            "cof": -0.05624577166512722,
            "conflict": -0.028070194160649434
        },
        {
            "fid": 52,
            "cof": 0.05144712504198702,
            "conflict": -0.04253759517025154
        },
        {
            "fid": 10,
            "cof": 0.047347034487062845,
            "conflict": -0.019133643410847834
        },
        {
            "fid": 15,
            "cof": 0.04507716042409274,
            "conflict": -0.09152006086217031
        }
    ]
}