{
    "label": 1,
    "score": 0.42444024597117314,
    "predict_proba": [
        0.96,
        0.1300701942222965,
        0.0,
        0.0,
        0.0,
        0.0,
        0.02
    ],
    "result": [
        {
            "fid": 0,
            "cof": -0.24786025672797576,
            "conflict": -0.1342283414690782
        },
        {
            "fid": 52,
            "cof": 0.1682979617033341,
            "conflict": 0.01941816443897774
        },
        {
            "fid": 51,
            "cof": 0.14194868624475374,
            "conflict": 0.013988975443943829
        },
        {
            "fid": 25,
            "cof": -0.13438863106773039,
            "conflict": -0.05210654670410421
        },
        {
            "fid": 15,
            "cof": 0.13162206965586368,
            "conflict": -0.047817002778328406
        },
        {
            "fid": 35,
            "cof": 0.10707545340753256,
            "conflict": 0.1123161330760953
        },
        {
            "fid": 38,
            "cof": -0.10012947501036464,
            "conflict": -0.03763670596486326
        },
        {
            "fid": 13,
            "cof": 0.09482001690184584,
            "conflict": -0.11267126646703668
        },
        {
            "fid": 53,
            "cof": 0.08501611483297083,
            "conflict": 0.008215421125407423
        },
        {
            "fid": 50,
            "cof": 0.0759508455880611,
            "conflict": 0.013690390453643793
        }
    ]
}