{
    "label": 1,
    "score": 0.1419960265600374,
    "predict_proba": [
        1.0,
        0.0,
        0.0,
        0.0,
        0.0,
        0.0,
        0.0
    ],
    "result": [
        {
            "fid": 0,
            "cof": -0.3917483353757079
        },
        {
            "fid": 14,
            "cof": 0.21721921672713101
        },
        {
            "fid": 34,
            "cof": -0.21380268926500404
        },
        {
            "fid": 31,
            "cof": -0.208157825366378
        },
        {
            "fid": 41,
            "cof": 0.1766307269005889
        },
        {
            "fid": 39,
            "cof": 0.17155606355618275
        },
        {
            "fid": 21,
            "cof": -0.17084213598997952
        },
        {
            "fid": 29,
            "cof": 0.16923571631949258
        },
        {
            "fid": 50,
            "cof": 0.14164376327914768
        },
        {
            "fid": 30,
            "cof": -0.1281097148829151
        }
    ]
}