{
    "label": 0,
    "score": 0.13363306249507034,
    "predict_proba": [
        2.0,
        0.0,
        0.0,
        0.0,
        0.0,
        0.0,
        0.0
    ],
    "result": [
        {
            "fid": 0,
            "cof": 1.5845729773521637,
            "conflict": 0.09083052898412607
        },
        {
            "fid": 38,
            "cof": 1.4106678722677948,
            "conflict": 0.0810503328888349
        },
        {
            "fid": 50,
            "cof": -0.8829329581597499,
            "conflict": -0.04426790913698209
        },
        {
            "fid": 21,
            "cof": -0.6441616648685733,
            "conflict": -0.02968384525429793
        },
        {
            "fid": 22,
            "cof": 0.5508589566372458,
            "conflict": 0.027737402942567126
        },
        {
            "fid": 32,
            "cof": 0.5477716527689238,
            "conflict": 0.03449315228461325
        },
        {
            "fid": 27,
            "cof": 0.5268986676463724,
            "conflict": 0.0342474958554826
        },
        {
            "fid": 20,
            "cof": 0.4470716220559713,
            "conflict": 0.038903401714261175
        },
        {
            "fid": 49,
            "cof": 0.4096820034207256,
            "conflict": 0.022312791271292164
        },
        {
            "fid": 19,
            "cof": 0.3621851843470121,
            "conflict": 0.021778215258973395
        }
    ]
}